SeeSun/Detect.py
SeeSun/Speech.py
SeeSun/__init__.py
SeeSun-0.0.2.dist-info/LICENSE
SeeSun-0.0.2.dist-info/METADATA
SeeSun-0.0.2.dist-info/WHEEL
SeeSun-0.0.2.dist-info/top_level.txt
SeeSun-0.0.2.dist-info/RECORD
