Metadata-Version: 2.1
Name: SeeSun
Version: 0.0.2
Summary: Package for building service based on speech recognition/synthesis , Object detection , OCR
Home-page: https://github.com/ineed-coffee?tab=repositories
Author: A-eye
Author-email: leey93ssu@gmail.com
License: MIT
Platform: UNKNOWN
Classifier: Programming Language :: Python :: 3
Classifier: License :: OSI Approved :: MIT License
Classifier: Operating System :: OS Independent
